serialclass/__init__.py
serialclass/serialclass.py
serialclass-0.0.2.121.dist-info/LICENSE
serialclass-0.0.2.121.dist-info/METADATA
serialclass-0.0.2.121.dist-info/WHEEL
serialclass-0.0.2.121.dist-info/top_level.txt
serialclass-0.0.2.121.dist-info/RECORD
