Metadata-Version: 2.1
Name: serialclass
Version: 0.0.2.121
Summary: A base class to get well-formatted serialized representations of child classes
Home-page: https://github.com/gavanaken/serialclass
Author: Greg Van Aken
Author-email: gavanaken@gmail.com
License: UNKNOWN
Platform: UNKNOWN
Classifier: Programming Language :: Python :: 3
Classifier: License :: OSI Approved :: MIT License
Classifier: Operating System :: OS Independent
Requires-Python: >=3.6
